{"links": [{"source": "x_0", "value": 132614.96687335687, "target": "y_0"}, {"source": "x_0", "value": 4296.469855682696, "target": "y_1"}, {"source": "x_0", "value": 22765.211508380205, "target": "y_2"}, {"source": "x_0", "value": 12321.737333625986, "target": "y_3"}, {"source": "x_0", "value": 21182.550858065428, "target": "y_4"}, {"source": "x_0", "value": 22168.00196306568, "target": "y_5"}, {"source": "x_0", "value": 46200.81425184912, "target": "y_6"}, {"source": "x_0", "value": 1167.039494996249, "target": "y_7"}, {"source": "x_0", "value": 23856.64804054029, "target": "y_8"}, {"source": "x_0", "value": 5455.037910940369, "target": "y_9"}, {"source": "x_0", "value": 17872.151031821413, "target": "y_10"}, {"source": "x_0", "value": 13927.095790987445, "target": "y_11"}, {"source": "x_0", "value": 3544.3627989573147, "target": "y_12"}, {"source": "x_0", "value": 4298.40656592778, "target": "y_13"}, {"source": "x_0", "value": 0.0, "target": "y_14"}, {"source": "x_0", "value": 0.0, "target": "y_15"}, {"source": "x_0", "value": 0.0, "target": "y_16"}, {"source": "x_1", "value": 6206.742428229243, "target": "y_0"}, {"source": "x_1", "value": 392.87868493799687, "target": "y_1"}, {"source": "x_1", "value": 1515.416148152893, "target": "y_2"}, {"source": "x_1", "value": 1049.3930459029698, "target": "y_3"}, {"source": "x_1", "value": 1485.4101659085018, "target": "y_4"}, {"source": "x_1", "value": 1901.2270662852056, "target": "y_5"}, {"source": "x_1", "value": 2459.3592627160256, "target": "y_6"}, {"source": "x_1", "value": 111.4185282566923, "target": "y_7"}, {"source": "x_1", "value": 1098.1511653096702, "target": "y_8"}, {"source": "x_1", "value": 479.93814834610185, "target": "y_9"}, {"source": "x_1", "value": 1040.9076963101463, "target": "y_10"}, {"source": "x_1", "value": 1002.1718947956955, "target": "y_11"}, {"source": "x_1", "value": 290.2695702470489, "target": "y_12"}, {"source": "x_1", "value": 175.57091012796153, "target": "y_13"}, {"source": "x_1", "value": 0.0, "target": "y_14"}, {"source": "x_1", "value": 0.0, "target": "y_15"}, {"source": "x_1", "value": 0.0, "target": "y_16"}, {"source": "x_2", "value": 31271.74331975964, "target": "y_0"}, {"source": "x_2", "value": 1284.8886110057479, "target": "y_1"}, {"source": "x_2", "value": 7505.7178811377435, "target": "y_2"}, {"source": "x_2", "value": 3776.5062149834757, "target": "y_3"}, {"source": "x_2", "value": 6210.759603163232, "target": "y_4"}, {"source": "x_2", "value": 6302.57924962138, "target": "y_5"}, {"source": "x_2", "value": 11688.208940675038, "target": "y_6"}, {"source": "x_2", "value": 440.54848961717977, "target": "y_7"}, {"source": "x_2", "value": 7310.813859894775, "target": "y_8"}, {"source": "x_2", "value": 1761.8653650685949, "target": "y_9"}, {"source": "x_2", "value": 5036.226777260143, "target": "y_10"}, {"source": "x_2", "value": 4047.243217659776, "target": "y_11"}, {"source": "x_2", "value": 932.7907220190393, "target": "y_12"}, {"source": "x_2", "value": 1338.4146118457697, "target": "y_13"}, {"source": "x_2", "value": 0.0, "target": "y_14"}, {"source": "x_2", "value": 0.0, "target": "y_15"}, {"source": "x_2", "value": 0.0, "target": "y_16"}, {"source": "x_3", "value": 12680.76481818607, "target": "y_0"}, {"source": "x_3", "value": 770.4447888059873, "target": "y_1"}, {"source": "x_3", "value": 3081.9311026704777, "target": "y_2"}, {"source": "x_3", "value": 1981.3669644850302, "target": "y_3"}, {"source": "x_3", "value": 2246.604077779696, "target": "y_4"}, {"source": "x_3", "value": 3271.6196669422065, "target": "y_5"}, {"source": "x_3", "value": 5030.738704226143, "target": "y_6"}, {"source": "x_3", "value": 218.5026107040188, "target": "y_7"}, {"source": "x_3", "value": 2575.406272460021, "target": "y_8"}, {"source": "x_3", "value": 986.1673811872831, "target": "y_9"}, {"source": "x_3", "value": 1828.4035468550494, "target": "y_10"}, {"source": "x_3", "value": 2073.491403945311, "target": "y_11"}, {"source": "x_3", "value": 655.4576149768462, "target": "y_12"}, {"source": "x_3", "value": 539.3582877161858, "target": "y_13"}, {"source": "x_3", "value": 0.0, "target": "y_14"}, {"source": "x_3", "value": 0.0, "target": "y_15"}, {"source": "x_3", "value": 0.0, "target": "y_16"}, {"source": "x_4", "value": 15828.87412163889, "target": "y_0"}, {"source": "x_4", "value": 689.7396723340703, "target": "y_1"}, {"source": "x_4", "value": 3710.40637855173, "target": "y_2"}, {"source": "x_4", "value": 1816.6866957250554, "target": "y_3"}, {"source": "x_4", "value": 4656.491434375547, "target": "y_4"}, {"source": "x_4", "value": 3244.8050066265178, "target": "y_5"}, {"source": "x_4", "value": 5788.6377607478635, "target": "y_6"}, {"source": "x_4", "value": 227.53244200275145, "target": "y_7"}, {"source": "x_4", "value": 2727.7986071320647, "target": "y_8"}, {"source": "x_4", "value": 939.0804315836114, "target": "y_9"}, {"source": "x_4", "value": 3500.433069759035, "target": "y_10"}, {"source": "x_4", "value": 1936.9655969309213, "target": "y_11"}, {"source": "x_4", "value": 509.1176941884362, "target": "y_12"}, {"source": "x_4", "value": 397.1277299712548, "target": "y_13"}, {"source": "x_4", "value": 0.0, "target": "y_14"}, {"source": "x_4", "value": 0.0, "target": "y_15"}, {"source": "x_4", "value": 0.0, "target": "y_16"}, {"source": "x_5", "value": 12849.344510677083, "target": "y_0"}, {"source": "x_5", "value": 722.3515544679384, "target": "y_1"}, {"source": "x_5", "value": 3153.3848265601923, "target": "y_2"}, {"source": "x_5", "value": 2293.695377339216, "target": "y_3"}, {"source": "x_5", "value": 2942.9156057009714, "target": "y_4"}, {"source": "x_5", "value": 3696.019075258863, "target": "y_5"}, {"source": "x_5", "value": 4960.243265264885, "target": "y_6"}, {"source": "x_5", "value": 216.89683050320625, "target": "y_7"}, {"source": "x_5", "value": 2587.574970654326, "target": "y_8"}, {"source": "x_5", "value": 990.6183055424555, "target": "y_9"}, {"source": "x_5", "value": 2158.2301384746884, "target": "y_10"}, {"source": "x_5", "value": 2233.7198508896486, "target": "y_11"}, {"source": "x_5", "value": 680.0304309246669, "target": "y_12"}, {"source": "x_5", "value": 583.5124485062934, "target": "y_13"}, {"source": "x_5", "value": 0.0, "target": "y_14"}, {"source": "x_5", "value": 0.0, "target": "y_15"}, {"source": "x_5", "value": 0.0, "target": "y_16"}, {"source": "x_6", "value": 32066.256474330257, "target": "y_0"}, {"source": "x_6", "value": 1287.5339923380416, "target": "y_1"}, {"source": "x_6", "value": 5877.855289925648, "target": "y_2"}, {"source": "x_6", "value": 3580.1365965858713, "target": "y_3"}, {"source": "x_6", "value": 5540.134598016793, "target": "y_4"}, {"source": "x_6", "value": 6312.2323487906815, "target": "y_5"}, {"source": "x_6", "value": 13147.563392345543, "target": "y_6"}, {"source": "x_6", "value": 327.2104229613315, "target": "y_7"}, {"source": "x_6", "value": 5129.296260428295, "target": "y_8"}, {"source": "x_6", "value": 1476.6553773799972, "target": "y_9"}, {"source": "x_6", "value": 4585.2143037903425, "target": "y_10"}, {"source": "x_6", "value": 4169.442073564343, "target": "y_11"}, {"source": "x_6", "value": 1072.0914744665474, "target": "y_12"}, {"source": "x_6", "value": 761.6676134776317, "target": "y_13"}, {"source": "x_6", "value": 0.0, "target": "y_14"}, {"source": "x_6", "value": 0.0, "target": "y_15"}, {"source": "x_6", "value": 0.0, "target": "y_16"}, {"source": "x_7", "value": 2698.0172624264533, "target": "y_0"}, {"source": "x_7", "value": 159.61829779909814, "target": "y_1"}, {"source": "x_7", "value": 764.9020632998162, "target": "y_2"}, {"source": "x_7", "value": 438.94256491997294, "target": "y_3"}, {"source": "x_7", "value": 748.1739242094934, "target": "y_4"}, {"source": "x_7", "value": 804.191154421404, "target": "y_5"}, {"source": "x_7", "value": 968.6068583777958, "target": "y_6"}, {"source": "x_7", "value": 66.94000933928854, "target": "y_7"}, {"source": "x_7", "value": 452.70569580659276, "target": "y_8"}, {"source": "x_7", "value": 257.9344588040272, "target": "y_9"}, {"source": "x_7", "value": 535.8763321312924, "target": "y_10"}, {"source": "x_7", "value": 406.07663480440254, "target": "y_11"}, {"source": "x_7", "value": 74.5007213039853, "target": "y_12"}, {"source": "x_7", "value": 31.69231598187934, "target": "y_13"}, {"source": "x_7", "value": 0.0, "target": "y_14"}, {"source": "x_7", "value": 0.0, "target": "y_15"}, {"source": "x_7", "value": 0.0, "target": "y_16"}, {"source": "x_8", "value": 36204.405200893445, "target": "y_0"}, {"source": "x_8", "value": 1419.1658013151234, "target": "y_1"}, {"source": "x_8", "value": 8000.707343110993, "target": "y_2"}, {"source": "x_8", "value": 4255.432968907986, "target": "y_3"}, {"source": "x_8", "value": 5790.4524010074365, "target": "y_4"}, {"source": "x_8", "value": 6862.634318836338, "target": "y_5"}, {"source": "x_8", "value": 12466.397627418726, "target": "y_6"}, {"source": "x_8", "value": 412.30331198577596, "target": "y_7"}, {"source": "x_8", "value": 8872.611610737484, "target": "y_8"}, {"source": "x_8", "value": 1984.3718799998305, "target": "y_9"}, {"source": "x_8", "value": 5150.380864143573, "target": "y_10"}, {"source": "x_8", "value": 4328.46493380573, "target": "y_11"}, {"source": "x_8", "value": 922.2138525097425, "target": "y_12"}, {"source": "x_8", "value": 1775.6363990287657, "target": "y_13"}, {"source": "x_8", "value": 0.0, "target": "y_14"}, {"source": "x_8", "value": 0.0, "target": "y_15"}, {"source": "x_8", "value": 0.0, "target": "y_16"}, {"source": "x_9", "value": 4523.327269546097, "target": "y_0"}, {"source": "x_9", "value": 285.77440625495683, "target": "y_1"}, {"source": "x_9", "value": 1054.6104369254767, "target": "y_2"}, {"source": "x_9", "value": 607.7547011517942, "target": "y_3"}, {"source": "x_9", "value": 857.2089259282612, "target": "y_4"}, {"source": "x_9", "value": 1126.5138505390612, "target": "y_5"}, {"source": "x_9", "value": 1878.6454788273813, "target": "y_6"}, {"source": "x_9", "value": 57.61049400744169, "target": "y_7"}, {"source": "x_9", "value": 918.5457223288987, "target": "y_8"}, {"source": "x_9", "value": 379.2009444402241, "target": "y_9"}, {"source": "x_9", "value": 692.7929990393842, "target": "y_10"}, {"source": "x_9", "value": 788.4506829495461, "target": "y_11"}, {"source": "x_9", "value": 349.88431349150875, "target": "y_12"}, {"source": "x_9", "value": 196.0995712754202, "target": "y_13"}, {"source": "x_9", "value": 0.0, "target": "y_14"}, {"source": "x_9", "value": 0.0, "target": "y_15"}, {"source": "x_9", "value": 0.0, "target": "y_16"}, {"source": "x_10", "value": 14927.138411391717, "target": "y_0"}, {"source": "x_10", "value": 569.575458145021, "target": "y_1"}, {"source": "x_10", "value": 3207.82972039614, "target": "y_2"}, {"source": "x_10", "value": 1529.2093632189647, "target": "y_3"}, {"source": "x_10", "value": 3745.16900381214, "target": "y_4"}, {"source": "x_10", "value": 2647.899991490987, "target": "y_5"}, {"source": "x_10", "value": 5399.4845048664065, "target": "y_6"}, {"source": "x_10", "value": 152.5418627986786, "target": "y_7"}, {"source": "x_10", "value": 2748.011968430301, "target": "y_8"}, {"source": "x_10", "value": 786.1229869100516, "target": "y_9"}, {"source": "x_10", "value": 3016.2435029519374, "target": "y_10"}, {"source": "x_10", "value": 1688.0605044377182, "target": "y_11"}, {"source": "x_10", "value": 447.5937691903002, "target": "y_12"}, {"source": "x_10", "value": 417.87062968476744, "target": "y_13"}, {"source": "x_10", "value": 0.0, "target": "y_14"}, {"source": "x_10", "value": 0.0, "target": "y_15"}, {"source": "x_10", "value": 0.0, "target": "y_16"}, {"source": "x_11", "value": 7300.766428452498, "target": "y_0"}, {"source": "x_11", "value": 432.8655314279213, "target": "y_1"}, {"source": "x_11", "value": 1962.075502986784, "target": "y_2"}, {"source": "x_11", "value": 1531.0461346015986, "target": "y_3"}, {"source": "x_11", "value": 1636.2883042834378, "target": "y_4"}, {"source": "x_11", "value": 2174.265737439412, "target": "y_5"}, {"source": "x_11", "value": 2884.3736799349044, "target": "y_6"}, {"source": "x_11", "value": 110.40078893891031, "target": "y_7"}, {"source": "x_11", "value": 1412.5586059338666, "target": "y_8"}, {"source": "x_11", "value": 645.9047520087626, "target": "y_9"}, {"source": "x_11", "value": 1204.4752585481858, "target": "y_10"}, {"source": "x_11", "value": 1434.1820031248967, "target": "y_11"}, {"source": "x_11", "value": 346.30925744068514, "target": "y_12"}, {"source": "x_11", "value": 258.61349253776166, "target": "y_13"}, {"source": "x_11", "value": 0.0, "target": "y_14"}, {"source": "x_11", "value": 0.0, "target": "y_15"}, {"source": "x_11", "value": 0.0, "target": "y_16"}, {"source": "x_12", "value": 822.4686294170091, "target": "y_0"}, {"source": "x_12", "value": 48.56814040552312, "target": "y_1"}, {"source": "x_12", "value": 174.46982815556797, "target": "y_2"}, {"source": "x_12", "value": 189.4058177301564, "target": "y_3"}, {"source": "x_12", "value": 146.41183026971964, "target": "y_4"}, {"source": "x_12", "value": 241.19647599703367, "target": "y_5"}, {"source": "x_12", "value": 357.8115779301764, "target": "y_6"}, {"source": "x_12", "value": 5.593186579060822, "target": "y_7"}, {"source": "x_12", "value": 111.01716295951145, "target": "y_8"}, {"source": "x_12", "value": 95.82648189864067, "target": "y_9"}, {"source": "x_12", "value": 138.2590031397714, "target": "y_10"}, {"source": "x_12", "value": 153.99768720271678, "target": "y_11"}, {"source": "x_12", "value": 66.38311398262897, "target": "y_12"}, {"source": "x_12", "value": 13.925019893498058, "target": "y_13"}, {"source": "x_12", "value": 0.0, "target": "y_14"}, {"source": "x_12", "value": 0.0, "target": "y_15"}, {"source": "x_12", "value": 0.0, "target": "y_16"}, {"source": "x_13", "value": 11215.263523105803, "target": "y_0"}, {"source": "x_13", "value": 514.5857395307224, "target": "y_1"}, {"source": "x_13", "value": 2611.5913161403864, "target": "y_2"}, {"source": "x_13", "value": 1294.364100307691, "target": "y_3"}, {"source": "x_13", "value": 1755.4296393085567, "target": "y_4"}, {"source": "x_13", "value": 2176.5909619993295, "target": "y_5"}, {"source": "x_13", "value": 3414.627271565734, "target": "y_6"}, {"source": "x_13", "value": 142.53626462706302, "target": "y_7"}, {"source": "x_13", "value": 2980.3077184241997, "target": "y_8"}, {"source": "x_13", "value": 708.3324684262184, "target": "y_9"}, {"source": "x_13", "value": 1666.3669020204138, "target": "y_10"}, {"source": "x_13", "value": 1208.5337494294663, "target": "y_11"}, {"source": "x_13", "value": 256.16316119293197, "target": "y_12"}, {"source": "x_13", "value": 854.8235586908995, "target": "y_13"}, {"source": "x_13", "value": 0.0, "target": "y_14"}, {"source": "x_13", "value": 0.0, "target": "y_15"}, {"source": "x_13", "value": 0.0, "target": "y_16"}, {"source": "x_14", "value": 0.0, "target": "y_0"}, {"source": "x_14", "value": 0.0, "target": "y_1"}, {"source": "x_14", "value": 0.0, "target": "y_2"}, {"source": "x_14", "value": 0.0, "target": "y_3"}, {"source": "x_14", "value": 0.0, "target": "y_4"}, {"source": "x_14", "value": 0.0, "target": "y_5"}, {"source": "x_14", "value": 0.0, "target": "y_6"}, {"source": "x_14", "value": 0.0, "target": "y_7"}, {"source": "x_14", "value": 0.0, "target": "y_8"}, {"source": "x_14", "value": 0.0, "target": "y_9"}, {"source": "x_14", "value": 0.0, "target": "y_10"}, {"source": "x_14", "value": 0.0, "target": "y_11"}, {"source": "x_14", "value": 0.0, "target": "y_12"}, {"source": "x_14", "value": 0.0, "target": "y_13"}, {"source": "x_14", "value": 0.0, "target": "y_14"}, {"source": "x_14", "value": 0.0, "target": "y_15"}, {"source": "x_14", "value": 0.0, "target": "y_16"}, {"source": "x_15", "value": 270.175966115808, "target": "y_0"}, {"source": "x_15", "value": 9.092939758079025, "target": "y_1"}, {"source": "x_15", "value": 60.23970725191128, "target": "y_2"}, {"source": "x_15", "value": 16.865120531701876, "target": "y_3"}, {"source": "x_15", "value": 66.38906628909805, "target": "y_4"}, {"source": "x_15", "value": 34.49016223694617, "target": "y_5"}, {"source": "x_15", "value": 104.26922030406313, "target": "y_6"}, {"source": "x_15", "value": 2.882208241458711, "target": "y_7"}, {"source": "x_15", "value": 51.74815970277954, "target": "y_8"}, {"source": "x_15", "value": 16.766900400325063, "target": "y_9"}, {"source": "x_15", "value": 50.31957605507767, "target": "y_10"}, {"source": "x_15", "value": 34.15055914071937, "target": "y_11"}, {"source": "x_15", "value": 5.135575138368807, "target": "y_12"}, {"source": "x_15", "value": 17.65520508106701, "target": "y_13"}, {"source": "x_15", "value": 0.0, "target": "y_14"}, {"source": "x_15", "value": 0.0, "target": "y_15"}, {"source": "x_15", "value": 0.0, "target": "y_16"}, {"source": "x_16", "value": 349.55864787300396, "target": "y_0"}, {"source": "x_16", "value": 24.35496066859255, "target": "y_1"}, {"source": "x_16", "value": 132.37559177928057, "target": "y_2"}, {"source": "x_16", "value": 71.84352902728268, "target": "y_3"}, {"source": "x_16", "value": 19.451021872305763, "target": "y_4"}, {"source": "x_16", "value": 140.08268975813596, "target": "y_5"}, {"source": "x_16", "value": 186.99727822910313, "target": "y_6"}, {"source": "x_16", "value": 7.419985739309615, "target": "y_7"}, {"source": "x_16", "value": 122.04447728898741, "target": "y_8"}, {"source": "x_16", "value": 0.0, "target": "y_9"}, {"source": "x_16", "value": 10.979559551303037, "target": "y_10"}, {"source": "x_16", "value": 86.03351333330502, "target": "y_11"}, {"source": "x_16", "value": 10.386963269831845, "target": "y_12"}, {"source": "x_16", "value": 36.106813378470164, "target": "y_13"}, {"source": "x_16", "value": 0.0, "target": "y_14"}, {"source": "x_16", "value": 0.0, "target": "y_15"}, {"source": "x_16", "value": 0.0, "target": "y_16"}], "labels": ["apoptoticProcess", "biogenesis", "biologicalAdhesion", "biologicalRegulation", "cellKilling", "cellularProcess", "developmentalProcess", "growth", "immuneSystemProcess", "localization", "locomotion", "metabolicProcess", "multicellularOrganismalProcess", "reproduction", "responsetoStimulus", "rhythmicProcess", "transcriptionFactors"], "nodes": [{"name": "x_0"}, {"name": "x_1"}, {"name": "x_2"}, {"name": "x_3"}, {"name": "x_4"}, {"name": "x_5"}, {"name": "x_6"}, {"name": "x_7"}, {"name": "x_8"}, {"name": "x_9"}, {"name": "x_10"}, {"name": "x_11"}, {"name": "x_12"}, {"name": "x_13"}, {"name": "x_14"}, {"name": "x_15"}, {"name": "x_16"}, {"name": "y_0"}, {"name": "y_1"}, {"name": "y_2"}, {"name": "y_3"}, {"name": "y_4"}, {"name": "y_5"}, {"name": "y_6"}, {"name": "y_7"}, {"name": "y_8"}, {"name": "y_9"}, {"name": "y_10"}, {"name": "y_11"}, {"name": "y_12"}, {"name": "y_13"}, {"name": "y_14"}, {"name": "y_15"}, {"name": "y_16"}]}