{"links": [{"source": "x_0", "value": 134654.66715179305, "target": "y_0"}, {"source": "x_0", "value": 5090.951440606401, "target": "y_1"}, {"source": "x_0", "value": 22389.083104242105, "target": "y_2"}, {"source": "x_0", "value": 12465.015000193827, "target": "y_3"}, {"source": "x_0", "value": 21758.507545724722, "target": "y_4"}, {"source": "x_0", "value": 22914.724266118883, "target": "y_5"}, {"source": "x_0", "value": 45926.51923880938, "target": "y_6"}, {"source": "x_0", "value": 1203.0245402712962, "target": "y_7"}, {"source": "x_0", "value": 24237.700580654277, "target": "y_8"}, {"source": "x_0", "value": 5812.007046006166, "target": "y_9"}, {"source": "x_0", "value": 18641.00071367868, "target": "y_10"}, {"source": "x_0", "value": 13525.319850700216, "target": "y_11"}, {"source": "x_0", "value": 4247.157256496164, "target": "y_12"}, {"source": "x_0", "value": 3943.964438699002, "target": "y_13"}, {"source": "x_0", "value": 0.0, "target": "y_14"}, {"source": "x_0", "value": 0.0, "target": "y_15"}, {"source": "x_0", "value": 0.0, "target": "y_16"}, {"source": "x_1", "value": 6456.794856599849, "target": "y_0"}, {"source": "x_1", "value": 519.5242794963125, "target": "y_1"}, {"source": "x_1", "value": 1502.913403816788, "target": "y_2"}, {"source": "x_1", "value": 1131.6989405839563, "target": "y_3"}, {"source": "x_1", "value": 1534.4988804764362, "target": "y_4"}, {"source": "x_1", "value": 2065.5174380952576, "target": "y_5"}, {"source": "x_1", "value": 2610.6186492460347, "target": "y_6"}, {"source": "x_1", "value": 148.20421913096607, "target": "y_7"}, {"source": "x_1", "value": 1104.805315350616, "target": "y_8"}, {"source": "x_1", "value": 529.0038638926328, "target": "y_9"}, {"source": "x_1", "value": 1086.5769346961463, "target": "y_10"}, {"source": "x_1", "value": 1082.7317029127544, "target": "y_11"}, {"source": "x_1", "value": 368.33929649194596, "target": "y_12"}, {"source": "x_1", "value": 160.74705387885524, "target": "y_13"}, {"source": "x_1", "value": 0.0, "target": "y_14"}, {"source": "x_1", "value": 0.0, "target": "y_15"}, {"source": "x_1", "value": 0.0, "target": "y_16"}, {"source": "x_2", "value": 32099.570413862875, "target": "y_0"}, {"source": "x_2", "value": 1657.2979612088375, "target": "y_1"}, {"source": "x_2", "value": 7331.006417472006, "target": "y_2"}, {"source": "x_2", "value": 4022.964307185302, "target": "y_3"}, {"source": "x_2", "value": 6383.368958843959, "target": "y_4"}, {"source": "x_2", "value": 6734.916096572882, "target": "y_5"}, {"source": "x_2", "value": 12067.244680673706, "target": "y_6"}, {"source": "x_2", "value": 483.4996174950023, "target": "y_7"}, {"source": "x_2", "value": 7386.058583796918, "target": "y_8"}, {"source": "x_2", "value": 1942.6157070052798, "target": "y_9"}, {"source": "x_2", "value": 5269.091632202322, "target": "y_10"}, {"source": "x_2", "value": 3939.24295585286, "target": "y_11"}, {"source": "x_2", "value": 1165.5493271669243, "target": "y_12"}, {"source": "x_2", "value": 1202.2265254731158, "target": "y_13"}, {"source": "x_2", "value": 0.0, "target": "y_14"}, {"source": "x_2", "value": 0.0, "target": "y_15"}, {"source": "x_2", "value": 0.0, "target": "y_16"}, {"source": "x_3", "value": 12181.292657332995, "target": "y_0"}, {"source": "x_3", "value": 921.4084074659343, "target": "y_1"}, {"source": "x_3", "value": 2860.1724500842593, "target": "y_2"}, {"source": "x_3", "value": 1914.9033463213439, "target": "y_3"}, {"source": "x_3", "value": 2320.510669578555, "target": "y_4"}, {"source": "x_3", "value": 3170.583467111196, "target": "y_5"}, {"source": "x_3", "value": 4943.741942641636, "target": "y_6"}, {"source": "x_3", "value": 196.0734580120819, "target": "y_7"}, {"source": "x_3", "value": 2380.169921253608, "target": "y_8"}, {"source": "x_3", "value": 1039.0650724535396, "target": "y_9"}, {"source": "x_3", "value": 1941.2899715539272, "target": "y_10"}, {"source": "x_3", "value": 1901.2337512416268, "target": "y_11"}, {"source": "x_3", "value": 736.0758742973243, "target": "y_12"}, {"source": "x_3", "value": 486.1511015993997, "target": "y_13"}, {"source": "x_3", "value": 0.0, "target": "y_14"}, {"source": "x_3", "value": 0.0, "target": "y_15"}, {"source": "x_3", "value": 0.0, "target": "y_16"}, {"source": "x_4", "value": 16538.525644942052, "target": "y_0"}, {"source": "x_4", "value": 843.4411303805626, "target": "y_1"}, {"source": "x_4", "value": 3531.566593386855, "target": "y_2"}, {"source": "x_4", "value": 1954.5163442898247, "target": "y_3"}, {"source": "x_4", "value": 5033.7082088627185, "target": "y_4"}, {"source": "x_4", "value": 3651.3314542769845, "target": "y_5"}, {"source": "x_4", "value": 6062.84352679723, "target": "y_6"}, {"source": "x_4", "value": 269.867710332988, "target": "y_7"}, {"source": "x_4", "value": 2679.261030706666, "target": "y_8"}, {"source": "x_4", "value": 1002.3002549234723, "target": "y_9"}, {"source": "x_4", "value": 3805.482154521511, "target": "y_10"}, {"source": "x_4", "value": 1912.8615192270665, "target": "y_11"}, {"source": "x_4", "value": 611.3417631187369, "target": "y_12"}, {"source": "x_4", "value": 351.7399376194354, "target": "y_13"}, {"source": "x_4", "value": 0.0, "target": "y_14"}, {"source": "x_4", "value": 0.0, "target": "y_15"}, {"source": "x_4", "value": 0.0, "target": "y_16"}, {"source": "x_5", "value": 13902.107988540602, "target": "y_0"}, {"source": "x_5", "value": 1014.1600914815533, "target": "y_1"}, {"source": "x_5", "value": 3390.7819564388997, "target": "y_2"}, {"source": "x_5", "value": 2444.7930044739273, "target": "y_3"}, {"source": "x_5", "value": 3291.4452761243215, "target": "y_4"}, {"source": "x_5", "value": 3923.427430483378, "target": "y_5"}, {"source": "x_5", "value": 5276.786272146765, "target": "y_6"}, {"source": "x_5", "value": 230.70889857485537, "target": "y_7"}, {"source": "x_5", "value": 2856.633862116059, "target": "y_8"}, {"source": "x_5", "value": 1197.4855773604022, "target": "y_9"}, {"source": "x_5", "value": 2497.067299117541, "target": "y_10"}, {"source": "x_5", "value": 2203.9718282469685, "target": "y_11"}, {"source": "x_5", "value": 808.3842978744976, "target": "y_12"}, {"source": "x_5", "value": 592.5287417670365, "target": "y_13"}, {"source": "x_5", "value": 0.0, "target": "y_14"}, {"source": "x_5", "value": 0.0, "target": "y_15"}, {"source": "x_5", "value": 0.0, "target": "y_16"}, {"source": "x_6", "value": 32098.01030961444, "target": "y_0"}, {"source": "x_6", "value": 1545.0406407994335, "target": "y_1"}, {"source": "x_6", "value": 5923.947354915163, "target": "y_2"}, {"source": "x_6", "value": 3506.1808390333817, "target": "y_3"}, {"source": "x_6", "value": 5551.023455453919, "target": "y_4"}, {"source": "x_6", "value": 6292.158807904728, "target": "y_5"}, {"source": "x_6", "value": 12797.835397873352, "target": "y_6"}, {"source": "x_6", "value": 278.66243389648054, "target": "y_7"}, {"source": "x_6", "value": 5322.418068709629, "target": "y_8"}, {"source": "x_6", "value": 1625.7772841878825, "target": "y_9"}, {"source": "x_6", "value": 4705.772539221454, "target": "y_10"}, {"source": "x_6", "value": 4017.355475006245, "target": "y_11"}, {"source": "x_6", "value": 1338.4825457301374, "target": "y_12"}, {"source": "x_6", "value": 663.8027144656777, "target": "y_13"}, {"source": "x_6", "value": 0.0, "target": "y_14"}, {"source": "x_6", "value": 0.0, "target": "y_15"}, {"source": "x_6", "value": 0.0, "target": "y_16"}, {"source": "x_7", "value": 2685.095147690068, "target": "y_0"}, {"source": "x_7", "value": 241.9854731210383, "target": "y_1"}, {"source": "x_7", "value": 694.8623001817227, "target": "y_2"}, {"source": "x_7", "value": 510.299467901685, "target": "y_3"}, {"source": "x_7", "value": 775.6272136813075, "target": "y_4"}, {"source": "x_7", "value": 839.4036263228168, "target": "y_5"}, {"source": "x_7", "value": 956.18553974483, "target": "y_6"}, {"source": "x_7", "value": 96.04562104795049, "target": "y_7"}, {"source": "x_7", "value": 403.0962108266102, "target": "y_8"}, {"source": "x_7", "value": 298.7533329701902, "target": "y_9"}, {"source": "x_7", "value": 573.1367934347765, "target": "y_10"}, {"source": "x_7", "value": 381.3569261372267, "target": "y_11"}, {"source": "x_7", "value": 111.22436681185015, "target": "y_12"}, {"source": "x_7", "value": 35.605852330387236, "target": "y_13"}, {"source": "x_7", "value": 0.0, "target": "y_14"}, {"source": "x_7", "value": 0.0, "target": "y_15"}, {"source": "x_7", "value": 0.0, "target": "y_16"}, {"source": "x_8", "value": 36369.47743527125, "target": "y_0"}, {"source": "x_8", "value": 1678.9405922367657, "target": "y_1"}, {"source": "x_8", "value": 7710.29849758156, "target": "y_2"}, {"source": "x_8", "value": 4371.143633415782, "target": "y_3"}, {"source": "x_8", "value": 5843.394175938153, "target": "y_4"}, {"source": "x_8", "value": 7067.853410014442, "target": "y_5"}, {"source": "x_8", "value": 12737.179623027672, "target": "y_6"}, {"source": "x_8", "value": 392.00865319205934, "target": "y_7"}, {"source": "x_8", "value": 8844.245441918021, "target": "y_8"}, {"source": "x_8", "value": 2088.9174577346803, "target": "y_9"}, {"source": "x_8", "value": 5338.742015621366, "target": "y_10"}, {"source": "x_8", "value": 4243.731364179363, "target": "y_11"}, {"source": "x_8", "value": 1157.2300603938395, "target": "y_12"}, {"source": "x_8", "value": 1600.0566876702646, "target": "y_13"}, {"source": "x_8", "value": 0.0, "target": "y_14"}, {"source": "x_8", "value": 0.0, "target": "y_15"}, {"source": "x_8", "value": 0.0, "target": "y_16"}, {"source": "x_9", "value": 4451.946625641937, "target": "y_0"}, {"source": "x_9", "value": 360.310332908112, "target": "y_1"}, {"source": "x_9", "value": 1054.0606863943783, "target": "y_2"}, {"source": "x_9", "value": 628.5518560575827, "target": "y_3"}, {"source": "x_9", "value": 812.0487096918694, "target": "y_4"}, {"source": "x_9", "value": 1203.5679169856621, "target": "y_5"}, {"source": "x_9", "value": 1976.4338291195363, "target": "y_6"}, {"source": "x_9", "value": 61.35408199161825, "target": "y_7"}, {"source": "x_9", "value": 940.8195176113858, "target": "y_8"}, {"source": "x_9", "value": 419.8754526461259, "target": "y_9"}, {"source": "x_9", "value": 700.0979774123005, "target": "y_10"}, {"source": "x_9", "value": 806.6176193563242, "target": "y_11"}, {"source": "x_9", "value": 382.6501794661232, "target": "y_12"}, {"source": "x_9", "value": 184.4746238298211, "target": "y_13"}, {"source": "x_9", "value": 0.0, "target": "y_14"}, {"source": "x_9", "value": 0.0, "target": "y_15"}, {"source": "x_9", "value": 0.0, "target": "y_16"}, {"source": "x_10", "value": 14900.784314769773, "target": "y_0"}, {"source": "x_10", "value": 642.5035116004356, "target": "y_1"}, {"source": "x_10", "value": 2809.874100930832, "target": "y_2"}, {"source": "x_10", "value": 1557.6396638241993, "target": "y_3"}, {"source": "x_10", "value": 3812.687879733361, "target": "y_4"}, {"source": "x_10", "value": 2742.5749353850038, "target": "y_5"}, {"source": "x_10", "value": 5522.914171266055, "target": "y_6"}, {"source": "x_10", "value": 143.83656730655235, "target": "y_7"}, {"source": "x_10", "value": 2592.6707946558854, "target": "y_8"}, {"source": "x_10", "value": 773.9674783298083, "target": "y_9"}, {"source": "x_10", "value": 3139.9596371506473, "target": "y_10"}, {"source": "x_10", "value": 1641.4094275799991, "target": "y_11"}, {"source": "x_10", "value": 557.0781698612645, "target": "y_12"}, {"source": "x_10", "value": 386.2129299539472, "target": "y_13"}, {"source": "x_10", "value": 0.0, "target": "y_14"}, {"source": "x_10", "value": 0.0, "target": "y_15"}, {"source": "x_10", "value": 0.0, "target": "y_16"}, {"source": "x_11", "value": 7319.676061229206, "target": "y_0"}, {"source": "x_11", "value": 580.4833651715002, "target": "y_1"}, {"source": "x_11", "value": 2014.3223377369877, "target": "y_2"}, {"source": "x_11", "value": 1535.258726913609, "target": "y_3"}, {"source": "x_11", "value": 1711.641331875477, "target": "y_4"}, {"source": "x_11", "value": 2142.520339441768, "target": "y_5"}, {"source": "x_11", "value": 2842.7095402509376, "target": "y_6"}, {"source": "x_11", "value": 139.46092277582292, "target": "y_7"}, {"source": "x_11", "value": 1522.9153984287098, "target": "y_8"}, {"source": "x_11", "value": 702.7497681435276, "target": "y_9"}, {"source": "x_11", "value": 1289.5312527744718, "target": "y_10"}, {"source": "x_11", "value": 1271.036844449519, "target": "y_11"}, {"source": "x_11", "value": 390.2380054977998, "target": "y_12"}, {"source": "x_11", "value": 230.7004708903248, "target": "y_13"}, {"source": "x_11", "value": 0.0, "target": "y_14"}, {"source": "x_11", "value": 0.0, "target": "y_15"}, {"source": "x_11", "value": 0.0, "target": "y_16"}, {"source": "x_12", "value": 1113.808424562334, "target": "y_0"}, {"source": "x_12", "value": 94.0788173517129, "target": "y_1"}, {"source": "x_12", "value": 333.52136828957913, "target": "y_2"}, {"source": "x_12", "value": 239.95401095578603, "target": "y_3"}, {"source": "x_12", "value": 229.11363471491504, "target": "y_4"}, {"source": "x_12", "value": 301.92151478162106, "target": "y_5"}, {"source": "x_12", "value": 449.98036718026555, "target": "y_6"}, {"source": "x_12", "value": 4.946614682519823, "target": "y_7"}, {"source": "x_12", "value": 199.2590306962797, "target": "y_8"}, {"source": "x_12", "value": 155.69098242777685, "target": "y_9"}, {"source": "x_12", "value": 205.13306228024234, "target": "y_10"}, {"source": "x_12", "value": 176.66072673156557, "target": "y_11"}, {"source": "x_12", "value": 73.98038209182535, "target": "y_12"}, {"source": "x_12", "value": 15.673118585306183, "target": "y_13"}, {"source": "x_12", "value": 0.0, "target": "y_14"}, {"source": "x_12", "value": 0.0, "target": "y_15"}, {"source": "x_12", "value": 0.0, "target": "y_16"}, {"source": "x_13", "value": 10603.332051048095, "target": "y_0"}, {"source": "x_13", "value": 650.3476388246312, "target": "y_1"}, {"source": "x_13", "value": 2316.9779478625564, "target": "y_2"}, {"source": "x_13", "value": 1345.8912627687898, "target": "y_3"}, {"source": "x_13", "value": 1756.2884336636498, "target": "y_4"}, {"source": "x_13", "value": 2153.4601242907956, "target": "y_5"}, {"source": "x_13", "value": 3383.8577908749394, "target": "y_6"}, {"source": "x_13", "value": 127.93420053919598, "target": "y_7"}, {"source": "x_13", "value": 2795.3783424719263, "target": "y_8"}, {"source": "x_13", "value": 758.0948680598345, "target": "y_9"}, {"source": "x_13", "value": 1697.7317057411306, "target": "y_10"}, {"source": "x_13", "value": 1202.2840982849443, "target": "y_11"}, {"source": "x_13", "value": 341.3967169200635, "target": "y_12"}, {"source": "x_13", "value": 750.897353038656, "target": "y_13"}, {"source": "x_13", "value": 0.0, "target": "y_14"}, {"source": "x_13", "value": 0.0, "target": "y_15"}, {"source": "x_13", "value": 0.0, "target": "y_16"}, {"source": "x_14", "value": 0.0, "target": "y_0"}, {"source": "x_14", "value": 0.0, "target": "y_1"}, {"source": "x_14", "value": 0.0, "target": "y_2"}, {"source": "x_14", "value": 0.0, "target": "y_3"}, {"source": "x_14", "value": 0.0, "target": "y_4"}, {"source": "x_14", "value": 0.0, "target": "y_5"}, {"source": "x_14", "value": 0.0, "target": "y_6"}, {"source": "x_14", "value": 0.0, "target": "y_7"}, {"source": "x_14", "value": 0.0, "target": "y_8"}, {"source": "x_14", "value": 0.0, "target": "y_9"}, {"source": "x_14", "value": 0.0, "target": "y_10"}, {"source": "x_14", "value": 0.0, "target": "y_11"}, {"source": "x_14", "value": 0.0, "target": "y_12"}, {"source": "x_14", "value": 0.0, "target": "y_13"}, {"source": "x_14", "value": 0.0, "target": "y_14"}, {"source": "x_14", "value": 0.0, "target": "y_15"}, {"source": "x_14", "value": 0.0, "target": "y_16"}, {"source": "x_15", "value": 276.67351155274997, "target": "y_0"}, {"source": "x_15", "value": 10.364717034050612, "target": "y_1"}, {"source": "x_15", "value": 44.27461270123057, "target": "y_2"}, {"source": "x_15", "value": 19.518059404410117, "target": "y_3"}, {"source": "x_15", "value": 75.86282270349302, "target": "y_4"}, {"source": "x_15", "value": 48.58895071658825, "target": "y_5"}, {"source": "x_15", "value": 110.69556649726545, "target": "y_6"}, {"source": "x_15", "value": 2.882208241458711, "target": "y_7"}, {"source": "x_15", "value": 42.60620435206058, "target": "y_8"}, {"source": "x_15", "value": 18.154229094000836, "target": "y_9"}, {"source": "x_15", "value": 60.9812190234869, "target": "y_10"}, {"source": "x_15", "value": 29.086344637989626, "target": "y_11"}, {"source": "x_15", "value": 5.65456648208989, "target": "y_12"}, {"source": "x_15", "value": 10.878405273733248, "target": "y_13"}, {"source": "x_15", "value": 0.0, "target": "y_14"}, {"source": "x_15", "value": 0.0, "target": "y_15"}, {"source": "x_15", "value": 0.0, "target": "y_16"}, {"source": "x_16", "value": 325.79938455799436, "target": "y_0"}, {"source": "x_16", "value": 25.678972216688067, "target": "y_1"}, {"source": "x_16", "value": 112.77519783311004, "target": "y_2"}, {"source": "x_16", "value": 73.76476821131719, "target": "y_3"}, {"source": "x_16", "value": 23.021783154284655, "target": "y_4"}, {"source": "x_16", "value": 121.02490303908044, "target": "y_5"}, {"source": "x_16", "value": 159.55358124493873, "target": "y_6"}, {"source": "x_16", "value": 5.343304294896793, "target": "y_7"}, {"source": "x_16", "value": 117.98918336010878, "target": "y_8"}, {"source": "x_16", "value": 0.0, "target": "y_9"}, {"source": "x_16", "value": 9.88437168693887, "target": "y_10"}, {"source": "x_16", "value": 77.70813991121888, "target": "y_11"}, {"source": "x_16", "value": 13.269815555766172, "target": "y_12"}, {"source": "x_16", "value": 38.02342657230429, "target": "y_13"}, {"source": "x_16", "value": 0.0, "target": "y_14"}, {"source": "x_16", "value": 0.0, "target": "y_15"}, {"source": "x_16", "value": 0.0, "target": "y_16"}], "labels": ["apoptoticProcess", "biogenesis", "biologicalAdhesion", "biologicalRegulation", "cellKilling", "cellularProcess", "developmentalProcess", "growth", "immuneSystemProcess", "localization", "locomotion", "metabolicProcess", "multicellularOrganismalProcess", "reproduction", "responsetoStimulus", "rhythmicProcess", "transcriptionFactors"], "nodes": [{"name": "x_0"}, {"name": "x_1"}, {"name": "x_2"}, {"name": "x_3"}, {"name": "x_4"}, {"name": "x_5"}, {"name": "x_6"}, {"name": "x_7"}, {"name": "x_8"}, {"name": "x_9"}, {"name": "x_10"}, {"name": "x_11"}, {"name": "x_12"}, {"name": "x_13"}, {"name": "x_14"}, {"name": "x_15"}, {"name": "x_16"}, {"name": "y_0"}, {"name": "y_1"}, {"name": "y_2"}, {"name": "y_3"}, {"name": "y_4"}, {"name": "y_5"}, {"name": "y_6"}, {"name": "y_7"}, {"name": "y_8"}, {"name": "y_9"}, {"name": "y_10"}, {"name": "y_11"}, {"name": "y_12"}, {"name": "y_13"}, {"name": "y_14"}, {"name": "y_15"}, {"name": "y_16"}]}